{
	"configurations" : 
	[
		{
			"directories" : 
			[
				{
					"build" : ".",
					"jsonFile" : "directory-.-Debug-d0094a50bb2071803777.json",
					"minimumCMakeVersion" : 
					{
						"string" : "3.14"
					},
					"projectIndex" : 0,
					"source" : ".",
					"targetIndexes" : 
					[
						0,
						1,
						2,
						3,
						4
					]
				}
			],
			"name" : "Debug",
			"projects" : 
			[
				{
					"directoryIndexes" : 
					[
						0
					],
					"name" : "firstProject",
					"targetIndexes" : 
					[
						0,
						1,
						2,
						3,
						4
					]
				}
			],
			"targets" : 
			[
				{
					"directoryIndex" : 0,
					"id" : "ALL_BUILD::@6890427a1f51a3e7e1df",
					"jsonFile" : "target-ALL_BUILD-Debug-7a395c91e2648be7f639.json",
					"name" : "ALL_BUILD",
					"projectIndex" : 0
				},
				{
					"directoryIndex" : 0,
					"id" : "ZERO_CHECK::@6890427a1f51a3e7e1df",
					"jsonFile" : "target-ZERO_CHECK-Debug-456ff4a9b47da8aa1092.json",
					"name" : "ZERO_CHECK",
					"projectIndex" : 0
				},
				{
					"directoryIndex" : 0,
					"id" : "flutter_assemble::@6890427a1f51a3e7e1df",
					"jsonFile" : "target-flutter_assemble-Debug-ac40c7e64a4c9135d453.json",
					"name" : "flutter_assemble",
					"projectIndex" : 0
				},
				{
					"directoryIndex" : 0,
					"id" : "flutter_wrapper_app::@6890427a1f51a3e7e1df",
					"jsonFile" : "target-flutter_wrapper_app-Debug-b5707f5ed9b92607d1c2.json",
					"name" : "flutter_wrapper_app",
					"projectIndex" : 0
				},
				{
					"directoryIndex" : 0,
					"id" : "flutter_wrapper_plugin::@6890427a1f51a3e7e1df",
					"jsonFile" : "target-flutter_wrapper_plugin-Debug-8e085c091a16aeb857d5.json",
					"name" : "flutter_wrapper_plugin",
					"projectIndex" : 0
				}
			]
		},
		{
			"directories" : 
			[
				{
					"build" : ".",
					"jsonFile" : "directory-.-Release-d0094a50bb2071803777.json",
					"minimumCMakeVersion" : 
					{
						"string" : "3.14"
					},
					"projectIndex" : 0,
					"source" : ".",
					"targetIndexes" : 
					[
						0,
						1,
						2,
						3,
						4
					]
				}
			],
			"name" : "Release",
			"projects" : 
			[
				{
					"directoryIndexes" : 
					[
						0
					],
					"name" : "firstProject",
					"targetIndexes" : 
					[
						0,
						1,
						2,
						3,
						4
					]
				}
			],
			"targets" : 
			[
				{
					"directoryIndex" : 0,
					"id" : "ALL_BUILD::@6890427a1f51a3e7e1df",
					"jsonFile" : "target-ALL_BUILD-Release-7a395c91e2648be7f639.json",
					"name" : "ALL_BUILD",
					"projectIndex" : 0
				},
				{
					"directoryIndex" : 0,
					"id" : "ZERO_CHECK::@6890427a1f51a3e7e1df",
					"jsonFile" : "target-ZERO_CHECK-Release-456ff4a9b47da8aa1092.json",
					"name" : "ZERO_CHECK",
					"projectIndex" : 0
				},
				{
					"directoryIndex" : 0,
					"id" : "flutter_assemble::@6890427a1f51a3e7e1df",
					"jsonFile" : "target-flutter_assemble-Release-ac40c7e64a4c9135d453.json",
					"name" : "flutter_assemble",
					"projectIndex" : 0
				},
				{
					"directoryIndex" : 0,
					"id" : "flutter_wrapper_app::@6890427a1f51a3e7e1df",
					"jsonFile" : "target-flutter_wrapper_app-Release-2daae35fe95dfe7f0af9.json",
					"name" : "flutter_wrapper_app",
					"projectIndex" : 0
				},
				{
					"directoryIndex" : 0,
					"id" : "flutter_wrapper_plugin::@6890427a1f51a3e7e1df",
					"jsonFile" : "target-flutter_wrapper_plugin-Release-404db09036703700974b.json",
					"name" : "flutter_wrapper_plugin",
					"projectIndex" : 0
				}
			]
		},
		{
			"directories" : 
			[
				{
					"build" : ".",
					"jsonFile" : "directory-.-MinSizeRel-d0094a50bb2071803777.json",
					"minimumCMakeVersion" : 
					{
						"string" : "3.14"
					},
					"projectIndex" : 0,
					"source" : ".",
					"targetIndexes" : 
					[
						0,
						1,
						2,
						3,
						4
					]
				}
			],
			"name" : "MinSizeRel",
			"projects" : 
			[
				{
					"directoryIndexes" : 
					[
						0
					],
					"name" : "firstProject",
					"targetIndexes" : 
					[
						0,
						1,
						2,
						3,
						4
					]
				}
			],
			"targets" : 
			[
				{
					"directoryIndex" : 0,
					"id" : "ALL_BUILD::@6890427a1f51a3e7e1df",
					"jsonFile" : "target-ALL_BUILD-MinSizeRel-7a395c91e2648be7f639.json",
					"name" : "ALL_BUILD",
					"projectIndex" : 0
				},
				{
					"directoryIndex" : 0,
					"id" : "ZERO_CHECK::@6890427a1f51a3e7e1df",
					"jsonFile" : "target-ZERO_CHECK-MinSizeRel-456ff4a9b47da8aa1092.json",
					"name" : "ZERO_CHECK",
					"projectIndex" : 0
				},
				{
					"directoryIndex" : 0,
					"id" : "flutter_assemble::@6890427a1f51a3e7e1df",
					"jsonFile" : "target-flutter_assemble-MinSizeRel-ac40c7e64a4c9135d453.json",
					"name" : "flutter_assemble",
					"projectIndex" : 0
				},
				{
					"directoryIndex" : 0,
					"id" : "flutter_wrapper_app::@6890427a1f51a3e7e1df",
					"jsonFile" : "target-flutter_wrapper_app-MinSizeRel-d8bf75dd6b517b46ade5.json",
					"name" : "flutter_wrapper_app",
					"projectIndex" : 0
				},
				{
					"directoryIndex" : 0,
					"id" : "flutter_wrapper_plugin::@6890427a1f51a3e7e1df",
					"jsonFile" : "target-flutter_wrapper_plugin-MinSizeRel-5e1fb1c62d85cf0bc83d.json",
					"name" : "flutter_wrapper_plugin",
					"projectIndex" : 0
				}
			]
		},
		{
			"directories" : 
			[
				{
					"build" : ".",
					"jsonFile" : "directory-.-RelWithDebInfo-d0094a50bb2071803777.json",
					"minimumCMakeVersion" : 
					{
						"string" : "3.14"
					},
					"projectIndex" : 0,
					"source" : ".",
					"targetIndexes" : 
					[
						0,
						1,
						2,
						3,
						4
					]
				}
			],
			"name" : "RelWithDebInfo",
			"projects" : 
			[
				{
					"directoryIndexes" : 
					[
						0
					],
					"name" : "firstProject",
					"targetIndexes" : 
					[
						0,
						1,
						2,
						3,
						4
					]
				}
			],
			"targets" : 
			[
				{
					"directoryIndex" : 0,
					"id" : "ALL_BUILD::@6890427a1f51a3e7e1df",
					"jsonFile" : "target-ALL_BUILD-RelWithDebInfo-7a395c91e2648be7f639.json",
					"name" : "ALL_BUILD",
					"projectIndex" : 0
				},
				{
					"directoryIndex" : 0,
					"id" : "ZERO_CHECK::@6890427a1f51a3e7e1df",
					"jsonFile" : "target-ZERO_CHECK-RelWithDebInfo-456ff4a9b47da8aa1092.json",
					"name" : "ZERO_CHECK",
					"projectIndex" : 0
				},
				{
					"directoryIndex" : 0,
					"id" : "flutter_assemble::@6890427a1f51a3e7e1df",
					"jsonFile" : "target-flutter_assemble-RelWithDebInfo-ac40c7e64a4c9135d453.json",
					"name" : "flutter_assemble",
					"projectIndex" : 0
				},
				{
					"directoryIndex" : 0,
					"id" : "flutter_wrapper_app::@6890427a1f51a3e7e1df",
					"jsonFile" : "target-flutter_wrapper_app-RelWithDebInfo-39d19d9dcb324b7e79e4.json",
					"name" : "flutter_wrapper_app",
					"projectIndex" : 0
				},
				{
					"directoryIndex" : 0,
					"id" : "flutter_wrapper_plugin::@6890427a1f51a3e7e1df",
					"jsonFile" : "target-flutter_wrapper_plugin-RelWithDebInfo-5d8144f105c8141c2c2f.json",
					"name" : "flutter_wrapper_plugin",
					"projectIndex" : 0
				}
			]
		}
	],
	"kind" : "codemodel",
	"paths" : 
	{
		"build" : "D:/Informatica/Flutter/Projects/Unihack2023/UniHack_2023/build",
		"source" : "D:/Informatica/Flutter/Projects/Unihack2023/UniHack_2023/unihack/windows/flutter"
	},
	"version" : 
	{
		"major" : 2,
		"minor" : 6
	}
}
